dbt_meshify/.gitignore
dbt_meshify/__init__.py
dbt_meshify/change.py
dbt_meshify/change_set_processor.py
dbt_meshify/cli.py
dbt_meshify/dbt.py
dbt_meshify/dbt_projects.py
dbt_meshify/exceptions.py
dbt_meshify/main.py
dbt_meshify/storage/__init__.py
dbt_meshify/storage/dbt_project_editors.py
dbt_meshify/storage/file_content_editors.py
dbt_meshify/storage/file_manager.py
dbt_meshify/storage/jinja_blocks.py
dbt_meshify/utilities/__init__.py
dbt_meshify/utilities/contractor.py
dbt_meshify/utilities/dependencies.py
dbt_meshify/utilities/grouper.py
dbt_meshify/utilities/linker.py
dbt_meshify/utilities/references.py
dbt_meshify/utilities/versioner.py
dbt_meshify-0.5.4.dist-info/LICENSE
dbt_meshify-0.5.4.dist-info/METADATA
dbt_meshify-0.5.4.dist-info/WHEEL
dbt_meshify-0.5.4.dist-info/entry_points.txt
dbt_meshify-0.5.4.dist-info/RECORD
