Metadata-Version: 2.1
Name: dbt-meshify
Version: 0.5.4
Summary: a package to upgrade dbt packages to the dbt mesh framework
License: Apache 2.0
Author: Dave Connors
Author-email: dave.connors@fishtownanalytics.com
Requires-Python: >=3.9,<4.0
Classifier: License :: Other/Proprietary License
Classifier: Programming Language :: Python :: 3
Classifier: Programming Language :: Python :: 3.9
Classifier: Programming Language :: Python :: 3.10
Classifier: Programming Language :: Python :: 3.11
Classifier: Programming Language :: Python :: 3.12
Provides-Extra: postgres
Requires-Dist: click (>=8.1.3,<9.0.0)
Requires-Dist: dbt-core (>=1.5.0,<2.0.0)
Requires-Dist: dbt-postgres (>=1.5.0,<2.0.0) ; extra == "postgres"
Requires-Dist: loguru (>=0.7.0,<0.8.0)
Requires-Dist: ruamel-yaml (>=0.17.31,<0.18.0)
